ytnb_embed/__init__.py
ytnb_embed/custom_exception.py
ytnb_embed/logger.py
ytnb_embed/youtube.py
ytnb_embed-1.0.3.dist-info/licenses/LICENSE
ytnb_embed-1.0.3.dist-info/METADATA
ytnb_embed-1.0.3.dist-info/WHEEL
ytnb_embed-1.0.3.dist-info/top_level.txt
ytnb_embed-1.0.3.dist-info/RECORD
