Metadata-Version: 2.4
Name: ytnb-embed
Version: 1.0.3
Summary: Embed youtube video inside notebook
Home-page: https://github.com/aatansen/ytnb-embed
Author: aatansen
Author-email: aatansen@gmail.com
License: MIT
Project-URL: Bug Tracker, https://github.com/aatansen/ytnb-embed/issues
Classifier: Programming Language :: Python :: 3
Classifier: Programming Language :: Python :: 3.10
Classifier: Programming Language :: Python :: 3.11
Classifier: Programming Language :: Python :: 3.12
Classifier: Programming Language :: Python :: 3.13
Classifier: Operating System :: OS Independent
Requires-Python: >=3.10
License-File: LICENSE
Requires-Dist: ensure==1.0.4
Requires-Dist: py-youtube==1.1.7
Provides-Extra: testing
Requires-Dist: pytest==9.0.2; extra == "testing"
Requires-Dist: tox==4.33.0; extra == "testing"
Requires-Dist: flake8==7.3.0; extra == "testing"
Requires-Dist: mypy==1.19.1; extra == "testing"
Dynamic: author
Dynamic: author-email
Dynamic: description
Dynamic: description-content-type
Dynamic: home-page
Dynamic: license-file
Dynamic: project-url
Dynamic: summary
